mcp_giga_checker/__init__.py
mcp_giga_checker/__main__.py
mcp_giga_checker/server.py
mcp_giga_checker-0.1.1.dist-info/METADATA
mcp_giga_checker-0.1.1.dist-info/WHEEL
mcp_giga_checker-0.1.1.dist-info/entry_points.txt
mcp_giga_checker-0.1.1.dist-info/top_level.txt
mcp_giga_checker-0.1.1.dist-info/RECORD
